{
"ref_values": [
{
"Scenary": "AGRICULTURAL",
"Water reference value": "NATIONAL",
"Soil reference value": "U.S.EPA  ",
"Sediment reference value": "REGIONAL "
}
],
"Th        ": [
{
"Local":   1,
"Time": "All",
"CFwater": ".00000E+00",
"CFsoil": ".00000E+00",
"Igeo_soil": " .00000E+00",
"EFsoil-  ": ".00000E+00",
"PIsoil": ".00000E+00",
"Igeo_sed": " .00000E+00",
"EFsed-  ": ".00000E+00",
"PI_sed": ".00000E+00"
},
{
"Local":   2,
"Time": "All",
"CFwater": ".00000E+00",
"CFsoil": ".00000E+00",
"Igeo_soil": " .00000E+00",
"EFsoil-  ": ".00000E+00",
"PIsoil": ".00000E+00",
"Igeo_sed": " .00000E+00",
"EFsed-  ": ".00000E+00",
"PI_sed": ".00000E+00"
}
],
"Pb        ": [
{
"Local":   1,
"Time":   1,
"CFwater": ".20000E+03",
"CFsoil": ".00000E+00",
"Igeo_soil": " .00000E+00",
"EFsoil-  ": ".00000E+00",
"PIsoil": ".00000E+00",
"Igeo_sed": " .00000E+00",
"EFsed-  ": ".00000E+00",
"PI_sed": ".00000E+00"
},
{
"Local":   1,
"Time":   2,
"CFwater": ".30000E+03",
"CFsoil": ".00000E+00",
"Igeo_soil": " .00000E+00",
"EFsoil-  ": ".00000E+00",
"PIsoil": ".00000E+00",
"Igeo_sed": " .00000E+00",
"EFsed-  ": ".00000E+00",
"PI_sed": ".00000E+00"
},
{
"Local":   2,
"Time":   1,
"CFwater": ".55000E+03",
"CFsoil": ".00000E+00",
"Igeo_soil": " .00000E+00",
"EFsoil-  ": ".00000E+00",
"PIsoil": ".00000E+00",
"Igeo_sed": " .00000E+00",
"EFsed-  ": ".00000E+00",
"PI_sed": ".00000E+00"
},
{
"Local":   2,
"Time":   2,
"CFwater": ".33000E+03",
"CFsoil": ".00000E+00",
"Igeo_soil": " .00000E+00",
"EFsoil-  ": ".00000E+00",
"PIsoil": ".00000E+00",
"Igeo_sed": " .00000E+00",
"EFsed-  ": ".00000E+00",
"PI_sed": ".00000E+00"
}
],
"Cd        ": [
{
"Local":   1,
"Time":   1,
"CFwater": ".20000E+04",
"CFsoil": ".00000E+00",
"Igeo_soil": " .00000E+00",
"EFsoil-  ": ".00000E+00",
"PIsoil": ".00000E+00",
"Igeo_sed": " .00000E+00",
"EFsed-  ": ".00000E+00",
"PI_sed": ".00000E+00"
},
{
"Local":   1,
"Time":   2,
"CFwater": ".30000E+04",
"CFsoil": ".00000E+00",
"Igeo_soil": " .00000E+00",
"EFsoil-  ": ".00000E+00",
"PIsoil": ".00000E+00",
"Igeo_sed": " .00000E+00",
"EFsed-  ": ".00000E+00",
"PI_sed": ".00000E+00"
},
{
"Local":   2,
"Time":   1,
"CFwater": ".55000E+04",
"CFsoil": ".00000E+00",
"Igeo_soil": " .00000E+00",
"EFsoil-  ": ".00000E+00",
"PIsoil": ".00000E+00",
"Igeo_sed": " .00000E+00",
"EFsed-  ": ".00000E+00",
"PI_sed": ".00000E+00"
},
{
"Local":   2,
"Time":   2,
"CFwater": ".33000E+04",
"CFsoil": ".00000E+00",
"Igeo_soil": " .00000E+00",
"EFsoil-  ": ".00000E+00",
"PIsoil": ".00000E+00",
"Igeo_sed": " .00000E+00",
"EFsed-  ": ".00000E+00",
"PI_sed": ".00000E+00"
}
]
}
